Metadata-Version: 2.1
Name: surface-equivalence
Version: 3
Summary: Finding surface equivalences
Home-page: http://github.com/niels-lubbes/surface_equivalence
Author: Niels Lubbes
License: MIT
Keywords: surface equivalences isomorphisms rational projective
Platform: UNKNOWN
Classifier: Development Status :: 3 - Alpha
Classifier: License :: OSI Approved :: MIT License
Classifier: Programming Language :: Python :: 3
Classifier: Topic :: Scientific/Engineering :: Mathematics
License-File: LICENSE
